[
{"cat" : "Session","pid" :3608,"tid" :3608,"dur" :822202,"ts" :1,"ph" : "X","name" :"model_loading_uri","args" : {}},
{"cat" : "Session","pid" :3608,"tid" :3608,"dur" :2020517,"ts" :822235,"ph" : "X","name" :"session_initialization","args" : {}},
{"cat" : "Node","pid" :3608,"tid" :3608,"dur" :0,"ts" :2844499,"ph" : "X","name" :"/features/features.1/Relu_output_0_nchwc_fence_before","args" : {"op_name" : "Conv"}},
{"cat" : "Node","pid" :3608,"tid" :3608,"dur" :665,"ts" :2844504,"ph" : "X","name" :"/features/features.1/Relu_output_0_nchwc_kernel_time","args" : {"thread_scheduling_stats" : {"main_thread": {"thread_pool_name": "session-139-intra-op", "thread_id": "139983991560000", "block_size": [1], "core": 0, "Distribution": 14, "DistributionEnqueue": 13, "Run": 405, "Wait": 192, "WaitRevoke": 1}, "sub_threads": {"139981095954176": {"num_run": 1, "core": 2},"139981104346880": {"num_run": 1, "core": 28},"139981725079296": {"num_run": 1, "core": 30},"139981733472000": {"num_run": 1, "core": 32},"139981935482624": {"num_run": 1, "core": 34},"139981927089920": {"num_run": 1, "core": 36},"139981918697216": {"num_run": 1, "core": 38},"139981910304512": {"num_run": 1, "core": 40},"139981901911808": {"num_run": 1, "core": 42},"139981893519104": {"num_run": 1, "core": 20},"139981885126400": {"num_run": 1, "core": 46},"139981876733696": {"num_run": 1, "core": 1},"139981868340992": {"num_run": 1, "core": 3},"139981859948288": {"num_run": 1, "core": 5},"139981775435520": {"num_run": 1, "core": 7},"139981767042816": {"num_run": 1, "core": 9},"139981758650112": {"num_run": 1, "core": 11},"139981750257408": {"num_run": 1, "core": 13},"139981741864704": {"num_run": 1, "core": 15},"139981087561472": {"num_run": 1, "core": 17},"139981079168768": {"num_run": 1, "core": 19},"139981070776064": {"num_run": 1, "core": 21},"139981062383360": {"num_run": 1, "core": 23}}},"output_type_shape" : [{"float":[1,64,224,224]}],"output_size" : "12845056","parameter_size" : "7168","activation_size" : "602112","node_index" : "62","input_type_shape" : [{"float":[1,3,224,224]},{"float":[64,3,3,3]},{"float":[64]}],"provider" : "CPUExecutionProvider","op_name" : "Conv"}},
{"cat" : "Node","pid" :3608,"tid" :3608,"dur" :0,"ts" :2845179,"ph" : "X","name" :"/features/features.1/Relu_output_0_nchwc_fence_after","args" : {"op_name" : "Conv"}},
{"cat" : "Node","pid" :3608,"tid" :3608,"dur" :0,"ts" :2845183,"ph" : "X","name" :"/features/features.3/Relu_output_0_nchwc_fence_before","args" : {"op_name" : "Conv"}},
{"cat" : "Node","pid" :3608,"tid" :3608,"dur" :5463,"ts" :2845185,"ph" : "X","name" :"/features/features.3/Relu_output_0_nchwc_kernel_time","args" : {"thread_scheduling_stats" : {"main_thread": {"thread_pool_name": "session-139-intra-op", "thread_id": "139983991560000", "block_size": [1], "core": 0, "Distribution": 0, "DistributionEnqueue": 0, "Run": 2699, "Wait": 2734, "WaitRevoke": 1}, "sub_threads": {"139981095954176": {"num_run": 2, "core": 2},"139981104346880": {"num_run": 2, "core": 28},"139981725079296": {"num_run": 2, "core": 30},"139981733472000": {"num_run": 2, "core": 32},"139981935482624": {"num_run": 2, "core": 34},"139981927089920": {"num_run": 2, "core": 36},"139981918697216": {"num_run": 2, "core": 38},"139981910304512": {"num_run": 2, "core": 40},"139981901911808": {"num_run": 2, "core": 42},"139981893519104": {"num_run": 2, "core": 20},"139981885126400": {"num_run": 2, "core": 46},"139981876733696": {"num_run": 2, "core": 1},"139981868340992": {"num_run": 2, "core": 3},"139981859948288": {"num_run": 2, "core": 5},"139981775435520": {"num_run": 2, "core": 7},"139981767042816": {"num_run": 2, "core": 9},"139981758650112": {"num_run": 2, "core": 11},"139981750257408": {"num_run": 2, "core": 13},"139981741864704": {"num_run": 2, "core": 15},"139981087561472": {"num_run": 2, "core": 17},"139981079168768": {"num_run": 2, "core": 19},"139981070776064": {"num_run": 2, "core": 21},"139981062383360": {"num_run": 2, "core": 23}}},"output_type_shape" : [{"float":[1,64,224,224]}],"output_size" : "12845056","parameter_size" : "147712","activation_size" : "12845056","node_index" : "63","input_type_shape" : [{"float":[1,64,224,224]},{"float":[64,64,3,3]},{"float":[64]}],"provider" : "CPUExecutionProvider","op_name" : "Conv"}},
{"cat" : "Node","pid" :3608,"tid" :3608,"dur" :0,"ts" :2850658,"ph" : "X","name" :"/features/features.3/Relu_output_0_nchwc_fence_after","args" : {"op_name" : "Conv"}},
{"cat" : "Node","pid" :3608,"tid" :3608,"dur" :0,"ts" :2850663,"ph" : "X","name" :"/features/features.4/MaxPool_output_0_nchwc_fence_before","args" : {"op_name" : "MaxPool"}},
{"cat" : "Node","pid" :3608,"tid" :3608,"dur" :194,"ts" :2850666,"ph" : "X","name" :"/features/features.4/MaxPool_output_0_nchwc_kernel_time","args" : {"thread_scheduling_stats" : {"main_thread": {"thread_pool_name": "session-139-intra-op", "thread_id": "139983991560000", "block_size": [1], "core": 0, "Distribution": 0, "DistributionEnqueue": 0, "Run": 131, "Wait": 39, "WaitRevoke": 1}, "sub_threads": {"139981095954176": {"num_run": 3, "core": 2},"139981104346880": {"num_run": 3, "core": 28},"139981725079296": {"num_run": 3, "core": 30},"139981733472000": {"num_run": 3, "core": 32},"139981935482624": {"num_run": 3, "core": 34},"139981927089920": {"num_run": 3, "core": 36},"139981918697216": {"num_run": 3, "core": 38},"139981910304512": {"num_run": 3, "core": 40},"139981901911808": {"num_run": 3, "core": 42},"139981893519104": {"num_run": 3, "core": 20},"139981885126400": {"num_run": 3, "core": 46},"139981876733696": {"num_run": 3, "core": 1},"139981868340992": {"num_run": 3, "core": 3},"139981859948288": {"num_run": 3, "core": 5},"139981775435520": {"num_run": 3, "core": 7},"139981767042816": {"num_run": 3, "core": 9},"139981758650112": {"num_run": 3, "core": 11},"139981750257408": {"num_run": 3, "core": 13},"139981741864704": {"num_run": 3, "core": 15},"139981087561472": {"num_run": 3, "core": 17},"139981079168768": {"num_run": 3, "core": 19},"139981070776064": {"num_run": 3, "core": 21},"139981062383360": {"num_run": 3, "core": 23}}},"output_type_shape" : [{"float":[1,64,112,112]}],"output_size" : "3211264","parameter_size" : "0","activation_size" : "12845056","node_index" : "64","input_type_shape" : [{"float":[1,64,224,224]}],"provider" : "CPUExecutionProvider","op_name" : "MaxPool"}},
{"cat" : "Node","pid" :3608,"tid" :3608,"dur" :0,"ts" :2850869,"ph" : "X","name" :"/features/features.4/MaxPool_output_0_nchwc_fence_after","args" : {"op_name" : "MaxPool"}},
{"cat" : "Node","pid" :3608,"tid" :3608,"dur" :0,"ts" :2850873,"ph" : "X","name" :"/features/features.6/Relu_output_0_nchwc_fence_before","args" : {"op_name" : "Conv"}},
{"cat" : "Node","pid" :3608,"tid" :3608,"dur" :2308,"ts" :2850875,"ph" : "X","name" :"/features/features.6/Relu_output_0_nchwc_kernel_time","args" : {"thread_scheduling_stats" : {"main_thread": {"thread_pool_name": "session-139-intra-op", "thread_id": "139983991560000", "block_size": [1], "core": 0, "Distribution": 0, "DistributionEnqueue": 0, "Run": 1028, "Wait": 1256, "WaitRevoke": 0}, "sub_threads": {"139981095954176": {"num_run": 4, "core": 2},"139981104346880": {"num_run": 4, "core": 28},"139981725079296": {"num_run": 4, "core": 30},"139981733472000": {"num_run": 4, "core": 32},"139981935482624": {"num_run": 4, "core": 34},"139981927089920": {"num_run": 4, "core": 36},"139981918697216": {"num_run": 4, "core": 38},"139981910304512": {"num_run": 4, "core": 40},"139981901911808": {"num_run": 4, "core": 42},"139981893519104": {"num_run": 4, "core": 20},"139981885126400": {"num_run": 4, "core": 46},"139981876733696": {"num_run": 4, "core": 1},"139981868340992": {"num_run": 4, "core": 3},"139981859948288": {"num_run": 4, "core": 5},"139981775435520": {"num_run": 4, "core": 7},"139981767042816": {"num_run": 4, "core": 9},"139981758650112": {"num_run": 4, "core": 11},"139981750257408": {"num_run": 4, "core": 13},"139981741864704": {"num_run": 4, "core": 15},"139981087561472": {"num_run": 4, "core": 17},"139981079168768": {"num_run": 4, "core": 19},"139981070776064": {"num_run": 4, "core": 21},"139981062383360": {"num_run": 4, "core": 23}}},"output_type_shape" : [{"float":[1,128,112,112]}],"output_size" : "6422528","parameter_size" : "295424","activation_size" : "3211264","node_index" : "65","input_type_shape" : [{"float":[1,64,112,112]},{"float":[128,64,3,3]},{"float":[128]}],"provider" : "CPUExecutionProvider","op_name" : "Conv"}},
{"cat" : "Node","pid" :3608,"tid" :3608,"dur" :0,"ts" :2853192,"ph" : "X","name" :"/features/features.6/Relu_output_0_nchwc_fence_after","args" : {"op_name" : "Conv"}},
{"cat" : "Node","pid" :3608,"tid" :3608,"dur" :0,"ts" :2853195,"ph" : "X","name" :"/features/features.8/Relu_output_0_nchwc_fence_before","args" : {"op_name" : "Conv"}},
{"cat" : "Node","pid" :3608,"tid" :3608,"dur" :4594,"ts" :2853197,"ph" : "X","name" :"/features/features.8/Relu_output_0_nchwc_kernel_time","args" : {"thread_scheduling_stats" : {"main_thread": {"thread_pool_name": "session-139-intra-op", "thread_id": "139983991560000", "block_size": [1], "core": 0, "Distribution": 0, "DistributionEnqueue": 0, "Run": 2066, "Wait": 2504, "WaitRevoke": 1}, "sub_threads": {"139981095954176": {"num_run": 5, "core": 2},"139981104346880": {"num_run": 5, "core": 28},"139981725079296": {"num_run": 5, "core": 30},"139981733472000": {"num_run": 5, "core": 32},"139981935482624": {"num_run": 5, "core": 34},"139981927089920": {"num_run": 5, "core": 36},"139981918697216": {"num_run": 5, "core": 38},"139981910304512": {"num_run": 5, "core": 40},"139981901911808": {"num_run": 5, "core": 42},"139981893519104": {"num_run": 5, "core": 20},"139981885126400": {"num_run": 5, "core": 46},"139981876733696": {"num_run": 5, "core": 1},"139981868340992": {"num_run": 5, "core": 3},"139981859948288": {"num_run": 5, "core": 5},"139981775435520": {"num_run": 5, "core": 7},"139981767042816": {"num_run": 5, "core": 9},"139981758650112": {"num_run": 5, "core": 11},"139981750257408": {"num_run": 5, "core": 13},"139981741864704": {"num_run": 5, "core": 15},"139981087561472": {"num_run": 5, "core": 17},"139981079168768": {"num_run": 5, "core": 19},"139981070776064": {"num_run": 5, "core": 21},"139981062383360": {"num_run": 5, "core": 23}}},"output_type_shape" : [{"float":[1,128,112,112]}],"output_size" : "6422528","parameter_size" : "590336","activation_size" : "6422528","node_index" : "66","input_type_shape" : [{"float":[1,128,112,112]},{"float":[128,128,3,3]},{"float":[128]}],"provider" : "CPUExecutionProvider","op_name" : "Conv"}},
{"cat" : "Node","pid" :3608,"tid" :3608,"dur" :0,"ts" :2857799,"ph" : "X","name" :"/features/features.8/Relu_output_0_nchwc_fence_after","args" : {"op_name" : "Conv"}},
{"cat" : "Node","pid" :3608,"tid" :3608,"dur" :0,"ts" :2857808,"ph" : "X","name" :"/features/features.9/MaxPool_output_0_nchwc_fence_before","args" : {"op_name" : "MaxPool"}},
{"cat" : "Node","pid" :3608,"tid" :3608,"dur" :134,"ts" :2857810,"ph" : "X","name" :"/features/features.9/MaxPool_output_0_nchwc_kernel_time","args" : {"thread_scheduling_stats" : {"main_thread": {"thread_pool_name": "session-139-intra-op", "thread_id": "139983991560000", "block_size": [1], "core": 0, "Distribution": 0, "DistributionEnqueue": 0, "Run": 70, "Wait": 44, "WaitRevoke": 2}, "sub_threads": {"139981095954176": {"num_run": 6, "core": 2},"139981104346880": {"num_run": 6, "core": 28},"139981725079296": {"num_run": 6, "core": 30},"139981733472000": {"num_run": 6, "core": 32},"139981935482624": {"num_run": 6, "core": 34},"139981927089920": {"num_run": 6, "core": 36},"139981918697216": {"num_run": 6, "core": 38},"139981910304512": {"num_run": 6, "core": 40},"139981901911808": {"num_run": 6, "core": 42},"139981893519104": {"num_run": 6, "core": 20},"139981885126400": {"num_run": 6, "core": 46},"139981876733696": {"num_run": 6, "core": 1},"139981868340992": {"num_run": 6, "core": 3},"139981859948288": {"num_run": 6, "core": 5},"139981775435520": {"num_run": 6, "core": 7},"139981767042816": {"num_run": 6, "core": 9},"139981758650112": {"num_run": 6, "core": 11},"139981750257408": {"num_run": 6, "core": 13},"139981741864704": {"num_run": 6, "core": 15},"139981087561472": {"num_run": 6, "core": 17},"139981079168768": {"num_run": 6, "core": 19},"139981070776064": {"num_run": 6, "core": 21},"139981062383360": {"num_run": 6, "core": 23}}},"output_type_shape" : [{"float":[1,128,56,56]}],"output_size" : "1605632","parameter_size" : "0","activation_size" : "6422528","node_index" : "67","input_type_shape" : [{"float":[1,128,112,112]}],"provider" : "CPUExecutionProvider","op_name" : "MaxPool"}},
{"cat" : "Node","pid" :3608,"tid" :3608,"dur" :0,"ts" :2857951,"ph" : "X","name" :"/features/features.9/MaxPool_output_0_nchwc_fence_after","args" : {"op_name" : "MaxPool"}},
{"cat" : "Node","pid" :3608,"tid" :3608,"dur" :0,"ts" :2857954,"ph" : "X","name" :"/features/features.11/Relu_output_0_nchwc_fence_before","args" : {"op_name" : "Conv"}},
{"cat" : "Node","pid" :3608,"tid" :3608,"dur" :1446,"ts" :2857956,"ph" : "X","name" :"/features/features.11/Relu_output_0_nchwc_kernel_time","args" : {"thread_scheduling_stats" : {"main_thread": {"thread_pool_name": "session-139-intra-op", "thread_id": "139983991560000", "block_size": [1], "core": 0, "Distribution": 0, "DistributionEnqueue": 0, "Run": 1052, "Wait": 370, "WaitRevoke": 0}, "sub_threads": {"139981095954176": {"num_run": 7, "core": 2},"139981104346880": {"num_run": 7, "core": 28},"139981725079296": {"num_run": 7, "core": 30},"139981733472000": {"num_run": 7, "core": 32},"139981935482624": {"num_run": 7, "core": 34},"139981927089920": {"num_run": 7, "core": 36},"139981918697216": {"num_run": 7, "core": 38},"139981910304512": {"num_run": 7, "core": 40},"139981901911808": {"num_run": 7, "core": 42},"139981893519104": {"num_run": 7, "core": 20},"139981885126400": {"num_run": 7, "core": 46},"139981876733696": {"num_run": 7, "core": 1},"139981868340992": {"num_run": 7, "core": 3},"139981859948288": {"num_run": 7, "core": 5},"139981775435520": {"num_run": 7, "core": 7},"139981767042816": {"num_run": 7, "core": 9},"139981758650112": {"num_run": 7, "core": 11},"139981750257408": {"num_run": 7, "core": 13},"139981741864704": {"num_run": 7, "core": 15},"139981087561472": {"num_run": 7, "core": 17},"139981079168768": {"num_run": 7, "core": 19},"139981070776064": {"num_run": 7, "core": 21},"139981062383360": {"num_run": 7, "core": 23}}},"output_type_shape" : [{"float":[1,256,56,56]}],"output_size" : "3211264","parameter_size" : "1180672","activation_size" : "1605632","node_index" : "68","input_type_shape" : [{"float":[1,128,56,56]},{"float":[256,128,3,3]},{"float":[256]}],"provider" : "CPUExecutionProvider","op_name" : "Conv"}},
{"cat" : "Node","pid" :3608,"tid" :3608,"dur" :0,"ts" :2859409,"ph" : "X","name" :"/features/features.11/Relu_output_0_nchwc_fence_after","args" : {"op_name" : "Conv"}},
{"cat" : "Node","pid" :3608,"tid" :3608,"dur" :0,"ts" :2859414,"ph" : "X","name" :"/features/features.13/Relu_output_0_nchwc_fence_before","args" : {"op_name" : "Conv"}},
{"cat" : "Node","pid" :3608,"tid" :3608,"dur" :2432,"ts" :2859415,"ph" : "X","name" :"/features/features.13/Relu_output_0_nchwc_kernel_time","args" : {"thread_scheduling_stats" : {"main_thread": {"thread_pool_name": "session-139-intra-op", "thread_id": "139983991560000", "block_size": [1], "core": 0, "Distribution": 0, "DistributionEnqueue": 0, "Run": 2072, "Wait": 336, "WaitRevoke": 0}, "sub_threads": {"139981095954176": {"num_run": 8, "core": 2},"139981104346880": {"num_run": 8, "core": 28},"139981725079296": {"num_run": 8, "core": 30},"139981733472000": {"num_run": 8, "core": 32},"139981935482624": {"num_run": 8, "core": 34},"139981927089920": {"num_run": 8, "core": 36},"139981918697216": {"num_run": 8, "core": 38},"139981910304512": {"num_run": 8, "core": 40},"139981901911808": {"num_run": 8, "core": 42},"139981893519104": {"num_run": 8, "core": 20},"139981885126400": {"num_run": 8, "core": 46},"139981876733696": {"num_run": 8, "core": 1},"139981868340992": {"num_run": 8, "core": 3},"139981859948288": {"num_run": 8, "core": 5},"139981775435520": {"num_run": 8, "core": 7},"139981767042816": {"num_run": 8, "core": 9},"139981758650112": {"num_run": 8, "core": 11},"139981750257408": {"num_run": 8, "core": 13},"139981741864704": {"num_run": 8, "core": 15},"139981087561472": {"num_run": 8, "core": 17},"139981079168768": {"num_run": 8, "core": 19},"139981070776064": {"num_run": 8, "core": 21},"139981062383360": {"num_run": 8, "core": 23}}},"output_type_shape" : [{"float":[1,256,56,56]}],"output_size" : "3211264","parameter_size" : "2360320","activation_size" : "3211264","node_index" : "69","input_type_shape" : [{"float":[1,256,56,56]},{"float":[256,256,3,3]},{"float":[256]}],"provider" : "CPUExecutionProvider","op_name" : "Conv"}},
{"cat" : "Node","pid" :3608,"tid" :3608,"dur" :0,"ts" :2861854,"ph" : "X","name" :"/features/features.13/Relu_output_0_nchwc_fence_after","args" : {"op_name" : "Conv"}},
{"cat" : "Node","pid" :3608,"tid" :3608,"dur" :0,"ts" :2861857,"ph" : "X","name" :"/features/features.15/Relu_output_0_nchwc_fence_before","args" : {"op_name" : "Conv"}},
{"cat" : "Node","pid" :3608,"tid" :3608,"dur" :2440,"ts" :2861859,"ph" : "X","name" :"/features/features.15/Relu_output_0_nchwc_kernel_time","args" : {"thread_scheduling_stats" : {"main_thread": {"thread_pool_name": "session-139-intra-op", "thread_id": "139983991560000", "block_size": [1], "core": 0, "Distribution": 0, "DistributionEnqueue": 0, "Run": 2078, "Wait": 338, "WaitRevoke": 0}, "sub_threads": {"139981095954176": {"num_run": 9, "core": 2},"139981104346880": {"num_run": 9, "core": 28},"139981725079296": {"num_run": 9, "core": 30},"139981733472000": {"num_run": 9, "core": 32},"139981935482624": {"num_run": 9, "core": 34},"139981927089920": {"num_run": 9, "core": 36},"139981918697216": {"num_run": 9, "core": 38},"139981910304512": {"num_run": 9, "core": 40},"139981901911808": {"num_run": 9, "core": 42},"139981893519104": {"num_run": 9, "core": 20},"139981885126400": {"num_run": 9, "core": 46},"139981876733696": {"num_run": 9, "core": 1},"139981868340992": {"num_run": 9, "core": 3},"139981859948288": {"num_run": 9, "core": 5},"139981775435520": {"num_run": 9, "core": 7},"139981767042816": {"num_run": 9, "core": 9},"139981758650112": {"num_run": 9, "core": 11},"139981750257408": {"num_run": 9, "core": 13},"139981741864704": {"num_run": 9, "core": 15},"139981087561472": {"num_run": 9, "core": 17},"139981079168768": {"num_run": 9, "core": 19},"139981070776064": {"num_run": 9, "core": 21},"139981062383360": {"num_run": 9, "core": 23}}},"output_type_shape" : [{"float":[1,256,56,56]}],"output_size" : "3211264","parameter_size" : "2360320","activation_size" : "3211264","node_index" : "70","input_type_shape" : [{"float":[1,256,56,56]},{"float":[256,256,3,3]},{"float":[256]}],"provider" : "CPUExecutionProvider","op_name" : "Conv"}},
{"cat" : "Node","pid" :3608,"tid" :3608,"dur" :0,"ts" :2864306,"ph" : "X","name" :"/features/features.15/Relu_output_0_nchwc_fence_after","args" : {"op_name" : "Conv"}},
{"cat" : "Node","pid" :3608,"tid" :3608,"dur" :0,"ts" :2864309,"ph" : "X","name" :"/features/features.17/Relu_output_0_nchwc_fence_before","args" : {"op_name" : "Conv"}},
{"cat" : "Node","pid" :3608,"tid" :3608,"dur" :2438,"ts" :2864311,"ph" : "X","name" :"/features/features.17/Relu_output_0_nchwc_kernel_time","args" : {"thread_scheduling_stats" : {"main_thread": {"thread_pool_name": "session-139-intra-op", "thread_id": "139983991560000", "block_size": [1], "core": 0, "Distribution": 0, "DistributionEnqueue": 0, "Run": 2082, "Wait": 332, "WaitRevoke": 0}, "sub_threads": {"139981095954176": {"num_run": 10, "core": 2},"139981104346880": {"num_run": 10, "core": 28},"139981725079296": {"num_run": 10, "core": 30},"139981733472000": {"num_run": 10, "core": 32},"139981935482624": {"num_run": 10, "core": 34},"139981927089920": {"num_run": 10, "core": 36},"139981918697216": {"num_run": 10, "core": 38},"139981910304512": {"num_run": 10, "core": 40},"139981901911808": {"num_run": 10, "core": 42},"139981893519104": {"num_run": 10, "core": 20},"139981885126400": {"num_run": 10, "core": 46},"139981876733696": {"num_run": 10, "core": 1},"139981868340992": {"num_run": 10, "core": 3},"139981859948288": {"num_run": 10, "core": 5},"139981775435520": {"num_run": 10, "core": 7},"139981767042816": {"num_run": 10, "core": 9},"139981758650112": {"num_run": 10, "core": 11},"139981750257408": {"num_run": 10, "core": 13},"139981741864704": {"num_run": 10, "core": 15},"139981087561472": {"num_run": 10, "core": 17},"139981079168768": {"num_run": 10, "core": 19},"139981070776064": {"num_run": 10, "core": 21},"139981062383360": {"num_run": 10, "core": 23}}},"output_type_shape" : [{"float":[1,256,56,56]}],"output_size" : "3211264","parameter_size" : "2360320","activation_size" : "3211264","node_index" : "71","input_type_shape" : [{"float":[1,256,56,56]},{"float":[256,256,3,3]},{"float":[256]}],"provider" : "CPUExecutionProvider","op_name" : "Conv"}},
{"cat" : "Node","pid" :3608,"tid" :3608,"dur" :0,"ts" :2866756,"ph" : "X","name" :"/features/features.17/Relu_output_0_nchwc_fence_after","args" : {"op_name" : "Conv"}},
{"cat" : "Node","pid" :3608,"tid" :3608,"dur" :0,"ts" :2866760,"ph" : "X","name" :"/features/features.18/MaxPool_output_0_nchwc_fence_before","args" : {"op_name" : "MaxPool"}},
{"cat" : "Node","pid" :3608,"tid" :3608,"dur" :70,"ts" :2866768,"ph" : "X","name" :"/features/features.18/MaxPool_output_0_nchwc_kernel_time","args" : {"thread_scheduling_stats" : {"main_thread": {"thread_pool_name": "session-139-intra-op", "thread_id": "139983991560000", "block_size": [1], "core": 0, "Distribution": 0, "DistributionEnqueue": 0, "Run": 28, "Wait": 22, "WaitRevoke": 1}, "sub_threads": {"139981095954176": {"num_run": 11, "core": 2},"139981104346880": {"num_run": 11, "core": 28},"139981725079296": {"num_run": 11, "core": 30},"139981733472000": {"num_run": 11, "core": 32},"139981935482624": {"num_run": 11, "core": 34},"139981927089920": {"num_run": 11, "core": 36},"139981918697216": {"num_run": 11, "core": 38},"139981910304512": {"num_run": 11, "core": 40},"139981901911808": {"num_run": 11, "core": 42},"139981893519104": {"num_run": 11, "core": 20},"139981885126400": {"num_run": 11, "core": 46},"139981876733696": {"num_run": 11, "core": 1},"139981868340992": {"num_run": 11, "core": 3},"139981859948288": {"num_run": 11, "core": 5},"139981775435520": {"num_run": 11, "core": 7},"139981767042816": {"num_run": 11, "core": 9},"139981758650112": {"num_run": 11, "core": 11},"139981750257408": {"num_run": 11, "core": 13},"139981741864704": {"num_run": 11, "core": 15},"139981087561472": {"num_run": 11, "core": 17},"139981079168768": {"num_run": 11, "core": 19},"139981070776064": {"num_run": 11, "core": 21},"139981062383360": {"num_run": 11, "core": 23}}},"output_type_shape" : [{"float":[1,256,28,28]}],"output_size" : "802816","parameter_size" : "0","activation_size" : "3211264","node_index" : "72","input_type_shape" : [{"float":[1,256,56,56]}],"provider" : "CPUExecutionProvider","op_name" : "MaxPool"}},
{"cat" : "Node","pid" :3608,"tid" :3608,"dur" :0,"ts" :2866845,"ph" : "X","name" :"/features/features.18/MaxPool_output_0_nchwc_fence_after","args" : {"op_name" : "MaxPool"}},
{"cat" : "Node","pid" :3608,"tid" :3608,"dur" :0,"ts" :2866848,"ph" : "X","name" :"/features/features.20/Relu_output_0_nchwc_fence_before","args" : {"op_name" : "Conv"}},
{"cat" : "Node","pid" :3608,"tid" :3608,"dur" :1318,"ts" :2866850,"ph" : "X","name" :"/features/features.20/Relu_output_0_nchwc_kernel_time","args" : {"thread_scheduling_stats" : {"main_thread": {"thread_pool_name": "session-139-intra-op", "thread_id": "139983991560000", "block_size": [1], "core": 0, "Distribution": 0, "DistributionEnqueue": 0, "Run": 1077, "Wait": 219, "WaitRevoke": 0}, "sub_threads": {"139981095954176": {"num_run": 12, "core": 2},"139981104346880": {"num_run": 12, "core": 28},"139981725079296": {"num_run": 12, "core": 30},"139981733472000": {"num_run": 12, "core": 32},"139981935482624": {"num_run": 12, "core": 34},"139981927089920": {"num_run": 12, "core": 36},"139981918697216": {"num_run": 12, "core": 38},"139981910304512": {"num_run": 12, "core": 40},"139981901911808": {"num_run": 12, "core": 42},"139981893519104": {"num_run": 12, "core": 20},"139981885126400": {"num_run": 12, "core": 46},"139981876733696": {"num_run": 12, "core": 1},"139981868340992": {"num_run": 12, "core": 3},"139981859948288": {"num_run": 12, "core": 5},"139981775435520": {"num_run": 12, "core": 7},"139981767042816": {"num_run": 12, "core": 9},"139981758650112": {"num_run": 12, "core": 11},"139981750257408": {"num_run": 12, "core": 13},"139981741864704": {"num_run": 12, "core": 15},"139981087561472": {"num_run": 12, "core": 17},"139981079168768": {"num_run": 12, "core": 19},"139981070776064": {"num_run": 12, "core": 21},"139981062383360": {"num_run": 12, "core": 23}}},"output_type_shape" : [{"float":[1,512,28,28]}],"output_size" : "1605632","parameter_size" : "4720640","activation_size" : "802816","node_index" : "73","input_type_shape" : [{"float":[1,256,28,28]},{"float":[512,256,3,3]},{"float":[512]}],"provider" : "CPUExecutionProvider","op_name" : "Conv"}},
{"cat" : "Node","pid" :3608,"tid" :3608,"dur" :0,"ts" :2868176,"ph" : "X","name" :"/features/features.20/Relu_output_0_nchwc_fence_after","args" : {"op_name" : "Conv"}},
{"cat" : "Node","pid" :3608,"tid" :3608,"dur" :0,"ts" :2868179,"ph" : "X","name" :"/features/features.22/Relu_output_0_nchwc_fence_before","args" : {"op_name" : "Conv"}},
{"cat" : "Node","pid" :3608,"tid" :3608,"dur" :2616,"ts" :2868181,"ph" : "X","name" :"/features/features.22/Relu_output_0_nchwc_kernel_time","args" : {"thread_scheduling_stats" : {"main_thread": {"thread_pool_name": "session-139-intra-op", "thread_id": "139983991560000", "block_size": [1], "core": 0, "Distribution": 0, "DistributionEnqueue": 0, "Run": 2154, "Wait": 438, "WaitRevoke": 0}, "sub_threads": {"139981095954176": {"num_run": 13, "core": 2},"139981104346880": {"num_run": 13, "core": 28},"139981725079296": {"num_run": 13, "core": 30},"139981733472000": {"num_run": 13, "core": 32},"139981935482624": {"num_run": 13, "core": 34},"139981927089920": {"num_run": 13, "core": 36},"139981918697216": {"num_run": 13, "core": 38},"139981910304512": {"num_run": 13, "core": 40},"139981901911808": {"num_run": 13, "core": 42},"139981893519104": {"num_run": 13, "core": 20},"139981885126400": {"num_run": 13, "core": 46},"139981876733696": {"num_run": 13, "core": 1},"139981868340992": {"num_run": 13, "core": 3},"139981859948288": {"num_run": 13, "core": 5},"139981775435520": {"num_run": 13, "core": 7},"139981767042816": {"num_run": 13, "core": 9},"139981758650112": {"num_run": 13, "core": 11},"139981750257408": {"num_run": 13, "core": 13},"139981741864704": {"num_run": 13, "core": 15},"139981087561472": {"num_run": 13, "core": 17},"139981079168768": {"num_run": 13, "core": 19},"139981070776064": {"num_run": 13, "core": 21},"139981062383360": {"num_run": 13, "core": 23}}},"output_type_shape" : [{"float":[1,512,28,28]}],"output_size" : "1605632","parameter_size" : "9439232","activation_size" : "1605632","node_index" : "74","input_type_shape" : [{"float":[1,512,28,28]},{"float":[512,512,3,3]},{"float":[512]}],"provider" : "CPUExecutionProvider","op_name" : "Conv"}},
{"cat" : "Node","pid" :3608,"tid" :3608,"dur" :0,"ts" :2870805,"ph" : "X","name" :"/features/features.22/Relu_output_0_nchwc_fence_after","args" : {"op_name" : "Conv"}},
{"cat" : "Node","pid" :3608,"tid" :3608,"dur" :0,"ts" :2870808,"ph" : "X","name" :"/features/features.24/Relu_output_0_nchwc_fence_before","args" : {"op_name" : "Conv"}},
{"cat" : "Node","pid" :3608,"tid" :3608,"dur" :2603,"ts" :2870810,"ph" : "X","name" :"/features/features.24/Relu_output_0_nchwc_kernel_time","args" : {"thread_scheduling_stats" : {"main_thread": {"thread_pool_name": "session-139-intra-op", "thread_id": "139983991560000", "block_size": [1], "core": 0, "Distribution": 0, "DistributionEnqueue": 0, "Run": 2149, "Wait": 431, "WaitRevoke": 0}, "sub_threads": {"139981095954176": {"num_run": 14, "core": 2},"139981104346880": {"num_run": 14, "core": 28},"139981725079296": {"num_run": 14, "core": 30},"139981733472000": {"num_run": 14, "core": 32},"139981935482624": {"num_run": 14, "core": 34},"139981927089920": {"num_run": 14, "core": 36},"139981918697216": {"num_run": 14, "core": 38},"139981910304512": {"num_run": 14, "core": 40},"139981901911808": {"num_run": 14, "core": 42},"139981893519104": {"num_run": 14, "core": 20},"139981885126400": {"num_run": 14, "core": 46},"139981876733696": {"num_run": 14, "core": 1},"139981868340992": {"num_run": 14, "core": 3},"139981859948288": {"num_run": 14, "core": 5},"139981775435520": {"num_run": 14, "core": 7},"139981767042816": {"num_run": 14, "core": 9},"139981758650112": {"num_run": 14, "core": 11},"139981750257408": {"num_run": 14, "core": 13},"139981741864704": {"num_run": 14, "core": 15},"139981087561472": {"num_run": 14, "core": 17},"139981079168768": {"num_run": 14, "core": 19},"139981070776064": {"num_run": 14, "core": 21},"139981062383360": {"num_run": 14, "core": 23}}},"output_type_shape" : [{"float":[1,512,28,28]}],"output_size" : "1605632","parameter_size" : "9439232","activation_size" : "1605632","node_index" : "75","input_type_shape" : [{"float":[1,512,28,28]},{"float":[512,512,3,3]},{"float":[512]}],"provider" : "CPUExecutionProvider","op_name" : "Conv"}},
{"cat" : "Node","pid" :3608,"tid" :3608,"dur" :0,"ts" :2873420,"ph" : "X","name" :"/features/features.24/Relu_output_0_nchwc_fence_after","args" : {"op_name" : "Conv"}},
{"cat" : "Node","pid" :3608,"tid" :3608,"dur" :0,"ts" :2873423,"ph" : "X","name" :"/features/features.26/Relu_output_0_nchwc_fence_before","args" : {"op_name" : "Conv"}},
{"cat" : "Node","pid" :3608,"tid" :3608,"dur" :2607,"ts" :2873425,"ph" : "X","name" :"/features/features.26/Relu_output_0_nchwc_kernel_time","args" : {"thread_scheduling_stats" : {"main_thread": {"thread_pool_name": "session-139-intra-op", "thread_id": "139983991560000", "block_size": [1], "core": 0, "Distribution": 0, "DistributionEnqueue": 0, "Run": 2153, "Wait": 432, "WaitRevoke": 0}, "sub_threads": {"139981095954176": {"num_run": 15, "core": 2},"139981104346880": {"num_run": 15, "core": 28},"139981725079296": {"num_run": 15, "core": 30},"139981733472000": {"num_run": 15, "core": 32},"139981935482624": {"num_run": 15, "core": 34},"139981927089920": {"num_run": 15, "core": 36},"139981918697216": {"num_run": 15, "core": 38},"139981910304512": {"num_run": 15, "core": 40},"139981901911808": {"num_run": 15, "core": 42},"139981893519104": {"num_run": 15, "core": 20},"139981885126400": {"num_run": 15, "core": 46},"139981876733696": {"num_run": 15, "core": 1},"139981868340992": {"num_run": 15, "core": 3},"139981859948288": {"num_run": 15, "core": 5},"139981775435520": {"num_run": 15, "core": 7},"139981767042816": {"num_run": 15, "core": 9},"139981758650112": {"num_run": 15, "core": 11},"139981750257408": {"num_run": 15, "core": 13},"139981741864704": {"num_run": 15, "core": 15},"139981087561472": {"num_run": 15, "core": 17},"139981079168768": {"num_run": 15, "core": 19},"139981070776064": {"num_run": 15, "core": 21},"139981062383360": {"num_run": 15, "core": 23}}},"output_type_shape" : [{"float":[1,512,28,28]}],"output_size" : "1605632","parameter_size" : "9439232","activation_size" : "1605632","node_index" : "76","input_type_shape" : [{"float":[1,512,28,28]},{"float":[512,512,3,3]},{"float":[512]}],"provider" : "CPUExecutionProvider","op_name" : "Conv"}},
{"cat" : "Node","pid" :3608,"tid" :3608,"dur" :0,"ts" :2876040,"ph" : "X","name" :"/features/features.26/Relu_output_0_nchwc_fence_after","args" : {"op_name" : "Conv"}},
{"cat" : "Node","pid" :3608,"tid" :3608,"dur" :0,"ts" :2876045,"ph" : "X","name" :"/features/features.27/MaxPool_output_0_nchwc_fence_before","args" : {"op_name" : "MaxPool"}},
{"cat" : "Node","pid" :3608,"tid" :3608,"dur" :51,"ts" :2876047,"ph" : "X","name" :"/features/features.27/MaxPool_output_0_nchwc_kernel_time","args" : {"thread_scheduling_stats" : {"main_thread": {"thread_pool_name": "session-139-intra-op", "thread_id": "139983991560000", "block_size": [1], "core": 0, "Distribution": 0, "DistributionEnqueue": 0, "Run": 27, "Wait": 4, "WaitRevoke": 1}, "sub_threads": {"139981095954176": {"num_run": 16, "core": 2},"139981104346880": {"num_run": 16, "core": 28},"139981725079296": {"num_run": 16, "core": 30},"139981733472000": {"num_run": 16, "core": 32},"139981935482624": {"num_run": 16, "core": 34},"139981927089920": {"num_run": 16, "core": 36},"139981918697216": {"num_run": 16, "core": 38},"139981910304512": {"num_run": 16, "core": 40},"139981901911808": {"num_run": 16, "core": 42},"139981893519104": {"num_run": 16, "core": 20},"139981885126400": {"num_run": 16, "core": 46},"139981876733696": {"num_run": 16, "core": 1},"139981868340992": {"num_run": 16, "core": 3},"139981859948288": {"num_run": 16, "core": 5},"139981775435520": {"num_run": 16, "core": 7},"139981767042816": {"num_run": 16, "core": 9},"139981758650112": {"num_run": 16, "core": 11},"139981750257408": {"num_run": 16, "core": 13},"139981741864704": {"num_run": 16, "core": 15},"139981087561472": {"num_run": 16, "core": 17},"139981079168768": {"num_run": 16, "core": 19},"139981070776064": {"num_run": 16, "core": 21},"139981062383360": {"num_run": 16, "core": 23}}},"output_type_shape" : [{"float":[1,512,14,14]}],"output_size" : "401408","parameter_size" : "0","activation_size" : "1605632","node_index" : "77","input_type_shape" : [{"float":[1,512,28,28]}],"provider" : "CPUExecutionProvider","op_name" : "MaxPool"}},
{"cat" : "Node","pid" :3608,"tid" :3608,"dur" :0,"ts" :2876105,"ph" : "X","name" :"/features/features.27/MaxPool_output_0_nchwc_fence_after","args" : {"op_name" : "MaxPool"}},
{"cat" : "Node","pid" :3608,"tid" :3608,"dur" :0,"ts" :2876110,"ph" : "X","name" :"/features/features.29/Relu_output_0_nchwc_fence_before","args" : {"op_name" : "Conv"}},
{"cat" : "Node","pid" :3608,"tid" :3608,"dur" :861,"ts" :2876111,"ph" : "X","name" :"/features/features.29/Relu_output_0_nchwc_kernel_time","args" : {"thread_scheduling_stats" : {"main_thread": {"thread_pool_name": "session-139-intra-op", "thread_id": "139983991560000", "block_size": [1], "core": 0, "Distribution": 0, "DistributionEnqueue": 0, "Run": 606, "Wait": 231, "WaitRevoke": 0}, "sub_threads": {"139981095954176": {"num_run": 17, "core": 2},"139981104346880": {"num_run": 17, "core": 28},"139981725079296": {"num_run": 17, "core": 30},"139981733472000": {"num_run": 17, "core": 32},"139981935482624": {"num_run": 17, "core": 34},"139981927089920": {"num_run": 17, "core": 36},"139981918697216": {"num_run": 17, "core": 38},"139981910304512": {"num_run": 17, "core": 40},"139981901911808": {"num_run": 17, "core": 42},"139981893519104": {"num_run": 17, "core": 20},"139981885126400": {"num_run": 17, "core": 46},"139981876733696": {"num_run": 17, "core": 1},"139981868340992": {"num_run": 17, "core": 3},"139981859948288": {"num_run": 17, "core": 5},"139981775435520": {"num_run": 17, "core": 7},"139981767042816": {"num_run": 17, "core": 9},"139981758650112": {"num_run": 17, "core": 11},"139981750257408": {"num_run": 17, "core": 13},"139981741864704": {"num_run": 17, "core": 15},"139981087561472": {"num_run": 17, "core": 17},"139981079168768": {"num_run": 17, "core": 19},"139981070776064": {"num_run": 17, "core": 21},"139981062383360": {"num_run": 17, "core": 23}}},"output_type_shape" : [{"float":[1,512,14,14]}],"output_size" : "401408","parameter_size" : "9439232","activation_size" : "401408","node_index" : "78","input_type_shape" : [{"float":[1,512,14,14]},{"float":[512,512,3,3]},{"float":[512]}],"provider" : "CPUExecutionProvider","op_name" : "Conv"}},
{"cat" : "Node","pid" :3608,"tid" :3608,"dur" :0,"ts" :2876979,"ph" : "X","name" :"/features/features.29/Relu_output_0_nchwc_fence_after","args" : {"op_name" : "Conv"}},
{"cat" : "Node","pid" :3608,"tid" :3608,"dur" :0,"ts" :2876983,"ph" : "X","name" :"/features/features.31/Relu_output_0_nchwc_fence_before","args" : {"op_name" : "Conv"}},
{"cat" : "Node","pid" :3608,"tid" :3608,"dur" :860,"ts" :2876985,"ph" : "X","name" :"/features/features.31/Relu_output_0_nchwc_kernel_time","args" : {"thread_scheduling_stats" : {"main_thread": {"thread_pool_name": "session-139-intra-op", "thread_id": "139983991560000", "block_size": [1], "core": 0, "Distribution": 0, "DistributionEnqueue": 0, "Run": 599, "Wait": 239, "WaitRevoke": 0}, "sub_threads": {"139981095954176": {"num_run": 18, "core": 2},"139981104346880": {"num_run": 18, "core": 28},"139981725079296": {"num_run": 18, "core": 30},"139981733472000": {"num_run": 18, "core": 32},"139981935482624": {"num_run": 18, "core": 34},"139981927089920": {"num_run": 18, "core": 36},"139981918697216": {"num_run": 18, "core": 38},"139981910304512": {"num_run": 18, "core": 40},"139981901911808": {"num_run": 18, "core": 42},"139981893519104": {"num_run": 18, "core": 20},"139981885126400": {"num_run": 18, "core": 46},"139981876733696": {"num_run": 18, "core": 1},"139981868340992": {"num_run": 18, "core": 3},"139981859948288": {"num_run": 18, "core": 5},"139981775435520": {"num_run": 18, "core": 7},"139981767042816": {"num_run": 18, "core": 9},"139981758650112": {"num_run": 18, "core": 11},"139981750257408": {"num_run": 18, "core": 13},"139981741864704": {"num_run": 18, "core": 15},"139981087561472": {"num_run": 18, "core": 17},"139981079168768": {"num_run": 18, "core": 19},"139981070776064": {"num_run": 18, "core": 21},"139981062383360": {"num_run": 18, "core": 23}}},"output_type_shape" : [{"float":[1,512,14,14]}],"output_size" : "401408","parameter_size" : "9439232","activation_size" : "401408","node_index" : "79","input_type_shape" : [{"float":[1,512,14,14]},{"float":[512,512,3,3]},{"float":[512]}],"provider" : "CPUExecutionProvider","op_name" : "Conv"}},
{"cat" : "Node","pid" :3608,"tid" :3608,"dur" :0,"ts" :2877852,"ph" : "X","name" :"/features/features.31/Relu_output_0_nchwc_fence_after","args" : {"op_name" : "Conv"}},
{"cat" : "Node","pid" :3608,"tid" :3608,"dur" :0,"ts" :2877855,"ph" : "X","name" :"/features/features.33/Relu_output_0_nchwc_fence_before","args" : {"op_name" : "Conv"}},
{"cat" : "Node","pid" :3608,"tid" :3608,"dur" :860,"ts" :2877857,"ph" : "X","name" :"/features/features.33/Relu_output_0_nchwc_kernel_time","args" : {"thread_scheduling_stats" : {"main_thread": {"thread_pool_name": "session-139-intra-op", "thread_id": "139983991560000", "block_size": [1], "core": 0, "Distribution": 0, "DistributionEnqueue": 0, "Run": 609, "Wait": 229, "WaitRevoke": 0}, "sub_threads": {"139981095954176": {"num_run": 19, "core": 2},"139981104346880": {"num_run": 19, "core": 28},"139981725079296": {"num_run": 19, "core": 30},"139981733472000": {"num_run": 19, "core": 32},"139981935482624": {"num_run": 19, "core": 34},"139981927089920": {"num_run": 19, "core": 36},"139981918697216": {"num_run": 19, "core": 38},"139981910304512": {"num_run": 19, "core": 40},"139981901911808": {"num_run": 19, "core": 42},"139981893519104": {"num_run": 19, "core": 20},"139981885126400": {"num_run": 19, "core": 46},"139981876733696": {"num_run": 19, "core": 1},"139981868340992": {"num_run": 19, "core": 3},"139981859948288": {"num_run": 19, "core": 5},"139981775435520": {"num_run": 19, "core": 7},"139981767042816": {"num_run": 19, "core": 9},"139981758650112": {"num_run": 19, "core": 11},"139981750257408": {"num_run": 19, "core": 13},"139981741864704": {"num_run": 19, "core": 15},"139981087561472": {"num_run": 19, "core": 17},"139981079168768": {"num_run": 19, "core": 19},"139981070776064": {"num_run": 19, "core": 21},"139981062383360": {"num_run": 19, "core": 23}}},"output_type_shape" : [{"float":[1,512,14,14]}],"output_size" : "401408","parameter_size" : "9439232","activation_size" : "401408","node_index" : "80","input_type_shape" : [{"float":[1,512,14,14]},{"float":[512,512,3,3]},{"float":[512]}],"provider" : "CPUExecutionProvider","op_name" : "Conv"}},
{"cat" : "Node","pid" :3608,"tid" :3608,"dur" :0,"ts" :2878723,"ph" : "X","name" :"/features/features.33/Relu_output_0_nchwc_fence_after","args" : {"op_name" : "Conv"}},
{"cat" : "Node","pid" :3608,"tid" :3608,"dur" :0,"ts" :2878726,"ph" : "X","name" :"/features/features.35/Relu_output_0_nchwc_fence_before","args" : {"op_name" : "Conv"}},
{"cat" : "Node","pid" :3608,"tid" :3608,"dur" :856,"ts" :2878728,"ph" : "X","name" :"/features/features.35/Relu_output_0_nchwc_kernel_time","args" : {"thread_scheduling_stats" : {"main_thread": {"thread_pool_name": "session-139-intra-op", "thread_id": "139983991560000", "block_size": [1], "core": 0, "Distribution": 0, "DistributionEnqueue": 0, "Run": 600, "Wait": 234, "WaitRevoke": 0}, "sub_threads": {"139981095954176": {"num_run": 20, "core": 2},"139981104346880": {"num_run": 20, "core": 28},"139981725079296": {"num_run": 20, "core": 30},"139981733472000": {"num_run": 20, "core": 32},"139981935482624": {"num_run": 20, "core": 34},"139981927089920": {"num_run": 20, "core": 36},"139981918697216": {"num_run": 20, "core": 38},"139981910304512": {"num_run": 20, "core": 40},"139981901911808": {"num_run": 20, "core": 42},"139981893519104": {"num_run": 20, "core": 20},"139981885126400": {"num_run": 20, "core": 46},"139981876733696": {"num_run": 20, "core": 1},"139981868340992": {"num_run": 20, "core": 3},"139981859948288": {"num_run": 20, "core": 5},"139981775435520": {"num_run": 20, "core": 7},"139981767042816": {"num_run": 20, "core": 9},"139981758650112": {"num_run": 20, "core": 11},"139981750257408": {"num_run": 20, "core": 13},"139981741864704": {"num_run": 20, "core": 15},"139981087561472": {"num_run": 20, "core": 17},"139981079168768": {"num_run": 20, "core": 19},"139981070776064": {"num_run": 20, "core": 21},"139981062383360": {"num_run": 20, "core": 23}}},"output_type_shape" : [{"float":[1,512,14,14]}],"output_size" : "401408","parameter_size" : "9439232","activation_size" : "401408","node_index" : "81","input_type_shape" : [{"float":[1,512,14,14]},{"float":[512,512,3,3]},{"float":[512]}],"provider" : "CPUExecutionProvider","op_name" : "Conv"}},
{"cat" : "Node","pid" :3608,"tid" :3608,"dur" :0,"ts" :2879592,"ph" : "X","name" :"/features/features.35/Relu_output_0_nchwc_fence_after","args" : {"op_name" : "Conv"}},
{"cat" : "Node","pid" :3608,"tid" :3608,"dur" :0,"ts" :2879597,"ph" : "X","name" :"/features/features.36/MaxPool_output_0_nchwc_fence_before","args" : {"op_name" : "MaxPool"}},
{"cat" : "Node","pid" :3608,"tid" :3608,"dur" :42,"ts" :2879599,"ph" : "X","name" :"/features/features.36/MaxPool_output_0_nchwc_kernel_time","args" : {"thread_scheduling_stats" : {"main_thread": {"thread_pool_name": "session-139-intra-op", "thread_id": "139983991560000", "block_size": [1], "core": 0, "Distribution": 0, "DistributionEnqueue": 0, "Run": 13, "Wait": 10, "WaitRevoke": 1}, "sub_threads": {"139981095954176": {"num_run": 21, "core": 2},"139981104346880": {"num_run": 21, "core": 28},"139981725079296": {"num_run": 21, "core": 30},"139981733472000": {"num_run": 21, "core": 32},"139981935482624": {"num_run": 21, "core": 34},"139981927089920": {"num_run": 21, "core": 36},"139981918697216": {"num_run": 21, "core": 38},"139981910304512": {"num_run": 21, "core": 40},"139981901911808": {"num_run": 21, "core": 42},"139981893519104": {"num_run": 21, "core": 20},"139981885126400": {"num_run": 21, "core": 46},"139981876733696": {"num_run": 21, "core": 1},"139981868340992": {"num_run": 21, "core": 3},"139981859948288": {"num_run": 21, "core": 5},"139981775435520": {"num_run": 21, "core": 7},"139981767042816": {"num_run": 21, "core": 9},"139981758650112": {"num_run": 21, "core": 11},"139981750257408": {"num_run": 21, "core": 13},"139981741864704": {"num_run": 21, "core": 15},"139981087561472": {"num_run": 21, "core": 17},"139981079168768": {"num_run": 21, "core": 19},"139981070776064": {"num_run": 21, "core": 21},"139981062383360": {"num_run": 21, "core": 23}}},"output_type_shape" : [{"float":[1,512,7,7]}],"output_size" : "100352","parameter_size" : "0","activation_size" : "401408","node_index" : "82","input_type_shape" : [{"float":[1,512,14,14]}],"provider" : "CPUExecutionProvider","op_name" : "MaxPool"}},
{"cat" : "Node","pid" :3608,"tid" :3608,"dur" :0,"ts" :2879648,"ph" : "X","name" :"/features/features.36/MaxPool_output_0_nchwc_fence_after","args" : {"op_name" : "MaxPool"}},
{"cat" : "Node","pid" :3608,"tid" :3608,"dur" :0,"ts" :2879662,"ph" : "X","name" :"/pre_logits/act1/Relu_output_0_nchwc_fence_before","args" : {"op_name" : "Conv"}},
{"cat" : "Node","pid" :3608,"tid" :3608,"dur" :7497,"ts" :2879664,"ph" : "X","name" :"/pre_logits/act1/Relu_output_0_nchwc_kernel_time","args" : {"thread_scheduling_stats" : {"main_thread": {"thread_pool_name": "session-139-intra-op", "thread_id": "139983991560000", "block_size": [1], "core": 0, "Distribution": 0, "DistributionEnqueue": 0, "Run": 5636, "Wait": 1819, "WaitRevoke": 2}, "sub_threads": {"139981095954176": {"num_run": 22, "core": 2},"139981104346880": {"num_run": 22, "core": 28},"139981725079296": {"num_run": 22, "core": 30},"139981733472000": {"num_run": 22, "core": 32},"139981935482624": {"num_run": 22, "core": 34},"139981927089920": {"num_run": 22, "core": 36},"139981918697216": {"num_run": 22, "core": 38},"139981910304512": {"num_run": 22, "core": 40},"139981901911808": {"num_run": 22, "core": 42},"139981893519104": {"num_run": 22, "core": 20},"139981885126400": {"num_run": 22, "core": 46},"139981876733696": {"num_run": 22, "core": 1},"139981868340992": {"num_run": 22, "core": 3},"139981859948288": {"num_run": 22, "core": 5},"139981775435520": {"num_run": 22, "core": 7},"139981767042816": {"num_run": 22, "core": 9},"139981758650112": {"num_run": 22, "core": 11},"139981750257408": {"num_run": 22, "core": 13},"139981741864704": {"num_run": 22, "core": 15},"139981087561472": {"num_run": 22, "core": 17},"139981079168768": {"num_run": 22, "core": 19},"139981070776064": {"num_run": 22, "core": 21},"139981062383360": {"num_run": 22, "core": 23}}},"output_type_shape" : [{"float":[1,4096,1,1]}],"output_size" : "16384","parameter_size" : "411058176","activation_size" : "100352","node_index" : "83","input_type_shape" : [{"float":[1,512,7,7]},{"float":[4096,512,7,7]},{"float":[4096]}],"provider" : "CPUExecutionProvider","op_name" : "Conv"}},
{"cat" : "Node","pid" :3608,"tid" :3608,"dur" :0,"ts" :2887174,"ph" : "X","name" :"/pre_logits/act1/Relu_output_0_nchwc_fence_after","args" : {"op_name" : "Conv"}},
{"cat" : "Node","pid" :3608,"tid" :3608,"dur" :0,"ts" :2887182,"ph" : "X","name" :"/pre_logits/act2/Relu_output_0_nchwc_fence_before","args" : {"op_name" : "Conv"}},
{"cat" : "Node","pid" :3608,"tid" :3608,"dur" :1292,"ts" :2887184,"ph" : "X","name" :"/pre_logits/act2/Relu_output_0_nchwc_kernel_time","args" : {"thread_scheduling_stats" : {"main_thread": {"thread_pool_name": "session-139-intra-op", "thread_id": "139983991560000", "block_size": [1], "core": 0, "Distribution": 1, "DistributionEnqueue": 0, "Run": 956, "Wait": 292, "WaitRevoke": 4}, "sub_threads": {"139981095954176": {"num_run": 23, "core": 2},"139981104346880": {"num_run": 23, "core": 28},"139981725079296": {"num_run": 23, "core": 30},"139981733472000": {"num_run": 23, "core": 32},"139981935482624": {"num_run": 23, "core": 34},"139981927089920": {"num_run": 23, "core": 36},"139981918697216": {"num_run": 23, "core": 38},"139981910304512": {"num_run": 23, "core": 40},"139981901911808": {"num_run": 23, "core": 42},"139981893519104": {"num_run": 23, "core": 20},"139981885126400": {"num_run": 23, "core": 46},"139981876733696": {"num_run": 23, "core": 1},"139981868340992": {"num_run": 23, "core": 3},"139981859948288": {"num_run": 23, "core": 5},"139981775435520": {"num_run": 23, "core": 7},"139981767042816": {"num_run": 23, "core": 9},"139981758650112": {"num_run": 23, "core": 11},"139981750257408": {"num_run": 23, "core": 13},"139981741864704": {"num_run": 23, "core": 15},"139981087561472": {"num_run": 23, "core": 17},"139981079168768": {"num_run": 23, "core": 19},"139981070776064": {"num_run": 23, "core": 21},"139981062383360": {"num_run": 23, "core": 23}}},"output_type_shape" : [{"float":[1,4096,1,1]}],"output_size" : "16384","parameter_size" : "67125248","activation_size" : "16384","node_index" : "84","input_type_shape" : [{"float":[1,4096,1,1]},{"float":[4096,4096,1,1]},{"float":[4096]}],"provider" : "CPUExecutionProvider","op_name" : "Conv"}},
{"cat" : "Node","pid" :3608,"tid" :3608,"dur" :0,"ts" :2888489,"ph" : "X","name" :"/pre_logits/act2/Relu_output_0_nchwc_fence_after","args" : {"op_name" : "Conv"}},
{"cat" : "Node","pid" :3608,"tid" :3608,"dur" :0,"ts" :2888493,"ph" : "X","name" :"/head/global_pool/pool/GlobalAveragePool_output_0_nchwc_fence_before","args" : {"op_name" : "GlobalAveragePool"}},
{"cat" : "Node","pid" :3608,"tid" :3608,"dur" :41,"ts" :2888495,"ph" : "X","name" :"/head/global_pool/pool/GlobalAveragePool_output_0_nchwc_kernel_time","args" : {"thread_scheduling_stats" : {"main_thread": {"thread_pool_name": "session-139-intra-op", "thread_id": "139983991560000", "block_size": [1], "core": 0, "Distribution": 1, "DistributionEnqueue": 0, "Run": 6, "Wait": 12, "WaitRevoke": 1}, "sub_threads": {"139981095954176": {"num_run": 24, "core": 2},"139981104346880": {"num_run": 24, "core": 28},"139981725079296": {"num_run": 24, "core": 30},"139981733472000": {"num_run": 24, "core": 32},"139981935482624": {"num_run": 24, "core": 34},"139981927089920": {"num_run": 24, "core": 36},"139981918697216": {"num_run": 24, "core": 38},"139981910304512": {"num_run": 24, "core": 40},"139981901911808": {"num_run": 24, "core": 42},"139981893519104": {"num_run": 24, "core": 20},"139981885126400": {"num_run": 24, "core": 46},"139981876733696": {"num_run": 24, "core": 1},"139981868340992": {"num_run": 24, "core": 3},"139981859948288": {"num_run": 24, "core": 5},"139981775435520": {"num_run": 24, "core": 7},"139981767042816": {"num_run": 24, "core": 9},"139981758650112": {"num_run": 24, "core": 11},"139981750257408": {"num_run": 24, "core": 13},"139981741864704": {"num_run": 24, "core": 15},"139981087561472": {"num_run": 24, "core": 17},"139981079168768": {"num_run": 24, "core": 19},"139981070776064": {"num_run": 24, "core": 21},"139981062383360": {"num_run": 24, "core": 23}}},"output_type_shape" : [{"float":[1,4096,1,1]}],"output_size" : "16384","parameter_size" : "0","activation_size" : "16384","node_index" : "85","input_type_shape" : [{"float":[1,4096,1,1]}],"provider" : "CPUExecutionProvider","op_name" : "GlobalAveragePool"}},
{"cat" : "Node","pid" :3608,"tid" :3608,"dur" :0,"ts" :2888543,"ph" : "X","name" :"/head/global_pool/pool/GlobalAveragePool_output_0_nchwc_fence_after","args" : {"op_name" : "GlobalAveragePool"}},
{"cat" : "Node","pid" :3608,"tid" :3608,"dur" :0,"ts" :2888546,"ph" : "X","name" :"ReorderOutput_fence_before","args" : {"op_name" : "ReorderOutput"}},
{"cat" : "Node","pid" :3608,"tid" :3608,"dur" :39,"ts" :2888548,"ph" : "X","name" :"ReorderOutput_kernel_time","args" : {"thread_scheduling_stats" : {"main_thread": {"thread_pool_name": "session-139-intra-op", "thread_id": "139983991560000", "block_size": [1], "core": 0, "Distribution": 1, "DistributionEnqueue": 0, "Run": 4, "Wait": 15, "WaitRevoke": 1}, "sub_threads": {"139981095954176": {"num_run": 25, "core": 2},"139981104346880": {"num_run": 25, "core": 28},"139981725079296": {"num_run": 25, "core": 30},"139981733472000": {"num_run": 25, "core": 32},"139981935482624": {"num_run": 25, "core": 34},"139981927089920": {"num_run": 25, "core": 36},"139981918697216": {"num_run": 25, "core": 38},"139981910304512": {"num_run": 25, "core": 40},"139981901911808": {"num_run": 25, "core": 42},"139981893519104": {"num_run": 25, "core": 20},"139981885126400": {"num_run": 25, "core": 46},"139981876733696": {"num_run": 25, "core": 1},"139981868340992": {"num_run": 25, "core": 3},"139981859948288": {"num_run": 25, "core": 5},"139981775435520": {"num_run": 25, "core": 7},"139981767042816": {"num_run": 25, "core": 9},"139981758650112": {"num_run": 25, "core": 11},"139981750257408": {"num_run": 25, "core": 13},"139981741864704": {"num_run": 25, "core": 15},"139981087561472": {"num_run": 25, "core": 17},"139981079168768": {"num_run": 25, "core": 19},"139981070776064": {"num_run": 25, "core": 21},"139981062383360": {"num_run": 25, "core": 23}}},"output_type_shape" : [{"float":[1,4096,1,1]}],"output_size" : "16384","parameter_size" : "0","activation_size" : "16384","node_index" : "86","input_type_shape" : [{"float":[1,4096,1,1]}],"provider" : "CPUExecutionProvider","op_name" : "ReorderOutput"}},
{"cat" : "Node","pid" :3608,"tid" :3608,"dur" :0,"ts" :2888594,"ph" : "X","name" :"ReorderOutput_fence_after","args" : {"op_name" : "ReorderOutput"}},
{"cat" : "Node","pid" :3608,"tid" :3608,"dur" :0,"ts" :2888599,"ph" : "X","name" :"/head/global_pool/flatten/Flatten_fence_before","args" : {"op_name" : "Flatten"}},
{"cat" : "Node","pid" :3608,"tid" :3608,"dur" :14,"ts" :2888601,"ph" : "X","name" :"/head/global_pool/flatten/Flatten_kernel_time","args" : {"thread_scheduling_stats" : {"main_thread": {"thread_pool_name": "session-139-intra-op", "thread_id": "139983991560000", "block_size": [], "core": 0, "Distribution": 0, "DistributionEnqueue": 0, "Run": 0, "Wait": 0, "WaitRevoke": 0}, "sub_threads": {"139981095954176": {"num_run": 25, "core": 2},"139981104346880": {"num_run": 25, "core": 28},"139981725079296": {"num_run": 25, "core": 30},"139981733472000": {"num_run": 25, "core": 32},"139981935482624": {"num_run": 25, "core": 34},"139981927089920": {"num_run": 25, "core": 36},"139981918697216": {"num_run": 25, "core": 38},"139981910304512": {"num_run": 25, "core": 40},"139981901911808": {"num_run": 25, "core": 42},"139981893519104": {"num_run": 25, "core": 20},"139981885126400": {"num_run": 25, "core": 46},"139981876733696": {"num_run": 25, "core": 1},"139981868340992": {"num_run": 25, "core": 3},"139981859948288": {"num_run": 25, "core": 5},"139981775435520": {"num_run": 25, "core": 7},"139981767042816": {"num_run": 25, "core": 9},"139981758650112": {"num_run": 25, "core": 11},"139981750257408": {"num_run": 25, "core": 13},"139981741864704": {"num_run": 25, "core": 15},"139981087561472": {"num_run": 25, "core": 17},"139981079168768": {"num_run": 25, "core": 19},"139981070776064": {"num_run": 25, "core": 21},"139981062383360": {"num_run": 25, "core": 23}}},"output_type_shape" : [{"float":[1,4096]}],"output_size" : "16384","parameter_size" : "0","activation_size" : "16384","node_index" : "42","input_type_shape" : [{"float":[1,4096,1,1]}],"provider" : "CPUExecutionProvider","op_name" : "Flatten"}},
{"cat" : "Node","pid" :3608,"tid" :3608,"dur" :0,"ts" :2888622,"ph" : "X","name" :"/head/global_pool/flatten/Flatten_fence_after","args" : {"op_name" : "Flatten"}},
{"cat" : "Node","pid" :3608,"tid" :3608,"dur" :0,"ts" :2888625,"ph" : "X","name" :"/head/fc/Gemm_fence_before","args" : {"op_name" : "Gemm"}},
{"cat" : "Node","pid" :3608,"tid" :3608,"dur" :310,"ts" :2888627,"ph" : "X","name" :"/head/fc/Gemm_kernel_time","args" : {"thread_scheduling_stats" : {"main_thread": {"thread_pool_name": "session-139-intra-op", "thread_id": "139983991560000", "block_size": [1], "core": 0, "Distribution": 0, "DistributionEnqueue": 0, "Run": 206, "Wait": 77, "WaitRevoke": 1}, "sub_threads": {"139981095954176": {"num_run": 26, "core": 2},"139981104346880": {"num_run": 26, "core": 28},"139981725079296": {"num_run": 26, "core": 30},"139981733472000": {"num_run": 26, "core": 32},"139981935482624": {"num_run": 26, "core": 34},"139981927089920": {"num_run": 26, "core": 36},"139981918697216": {"num_run": 26, "core": 38},"139981910304512": {"num_run": 26, "core": 40},"139981901911808": {"num_run": 26, "core": 42},"139981893519104": {"num_run": 26, "core": 20},"139981885126400": {"num_run": 26, "core": 46},"139981876733696": {"num_run": 26, "core": 1},"139981868340992": {"num_run": 26, "core": 3},"139981859948288": {"num_run": 26, "core": 5},"139981775435520": {"num_run": 26, "core": 7},"139981767042816": {"num_run": 25, "core": 9},"139981758650112": {"num_run": 25, "core": 11},"139981750257408": {"num_run": 25, "core": 13},"139981741864704": {"num_run": 25, "core": 15},"139981087561472": {"num_run": 25, "core": 17},"139981079168768": {"num_run": 25, "core": 19},"139981070776064": {"num_run": 25, "core": 21},"139981062383360": {"num_run": 25, "core": 23}}},"output_type_shape" : [{"float":[1,1000]}],"output_size" : "4000","parameter_size" : "4000","activation_size" : "16384","node_index" : "43","input_type_shape" : [{"float":[1,4096]},{"float":[1000]}],"provider" : "CPUExecutionProvider","op_name" : "Gemm"}},
{"cat" : "Node","pid" :3608,"tid" :3608,"dur" :0,"ts" :2888943,"ph" : "X","name" :"/head/fc/Gemm_fence_after","args" : {"op_name" : "Gemm"}},
{"cat" : "Session","pid" :3608,"tid" :3608,"dur" :44455,"ts" :2844497,"ph" : "X","name" :"SequentialExecutor::Execute","args" : {}},
{"cat" : "Session","pid" :3608,"tid" :3608,"dur" :44485,"ts" :2844476,"ph" : "X","name" :"model_run","args" : {}}
]
